transistor/__init__.py
transistor/client.py
transistor/objects.py
transistorfm-1.0.1.dist-info/LICENSE
transistorfm-1.0.1.dist-info/METADATA
transistorfm-1.0.1.dist-info/WHEEL
transistorfm-1.0.1.dist-info/top_level.txt
transistorfm-1.0.1.dist-info/RECORD
