Metadata-Version: 2.1
Name: transistorfm
Version: 1.0.1
Summary: A Python client for the Transistor.fm API
Author: Josh Griffiths
Author-email: josh@hakuna.co.uk
License: MIT
Requires: requests
License-File: LICENSE
